[
  {
    "action": {
      "input": {
        "branch": "main",
        "documentId": "28712d94-0301-4822-98fa-77a65114ef86",
        "meta": {},
        "model": "powerhouse/workstream",
        "name": "Powerhouse Workstream 2024",
        "protocolVersions": {
          "base-reducer": 2
        },
        "signing": {
          "createdAtUtcIso": "2026-03-23T18:54:45.357Z",
          "documentType": "powerhouse/workstream",
          "nonce": "",
          "publicKey": {},
          "signature": "28712d94-0301-4822-98fa-77a65114ef86"
        },
        "slug": "",
        "version": 0
      },
      "scope": "document",
      "type": "CREATE_DOCUMENT"
    },
    "error": null,
    "hash": "",
    "id": "d932993a331c0ba18f1bd867718b009a",
    "index": 0,
    "skip": 0,
    "timestampUtcMs": "2026-03-23T18:54:45.357Z"
  },
  {
    "action": {
      "input": {
        "clientId": "f4dc5c83-e85e-4827-97fe-9ab22ebf233d",
        "icon": "https://fusion.sky.money/_next/image?url=https%3A%2F%2Fmakerdao-ses.github.io%2Fecosystem-dashboard%2Fecosystem-actors%2FPOWERHOUSE%2FPOWERHOUSE_logo.png&w=3840&q=85",
        "name": "Powerhouse"
      },
      "scope": "global",
      "type": "EDIT_CLIENT_INFO"
    },
    "error": null,
    "hash": "pM4IWqwUqrokQ/2WDAZNXu1BsuQ=",
    "id": "06e008f39bb0d6ae96edab68be9e67ee",
    "index": 0,
    "skip": 0,
    "timestampUtcMs": "2026-03-23T18:55:03.189Z"
  },
  {
    "action": {
      "input": {
        "documentId": "28712d94-0301-4822-98fa-77a65114ef86",
        "fromVersion": 0,
        "initialState": {
          "auth": {},
          "document": {
            "hash": {
              "algorithm": "sha1",
              "encoding": "base64"
            },
            "version": 0
          },
          "global": {
            "alternativeProposals": [],
            "client": null,
            "code": null,
            "initialProposal": null,
            "paymentRequests": [],
            "paymentTerms": null,
            "rfp": null,
            "sow": null,
            "status": "RFP_DRAFT",
            "title": null
          },
          "local": {}
        },
        "model": "powerhouse/workstream",
        "toVersion": 1
      },
      "scope": "document",
      "type": "UPGRADE_DOCUMENT"
    },
    "error": null,
    "hash": "",
    "id": "185d15f750c0d6ea07505a8c96efa443",
    "index": 1,
    "skip": 0,
    "timestampUtcMs": "2026-03-23T18:54:45.357Z"
  },
  {
    "action": {
      "input": {
        "code": "PW25",
        "paymentTerms": "59020cb2-681c-4108-8827-e475de073eec",
        "sowId": "9253cbbd-7577-4c3a-bca6-f54c81c74242",
        "status": "AWARDED",
        "title": "Powerhouse Workstream 2024"
      },
      "scope": "global",
      "type": "EDIT_WORKSTREAM"
    },
    "error": null,
    "hash": "23HW+KkWnEcMe1LNmOpGaOWJ2j0=",
    "id": "dfb11a509dd2a3d0169fba7567f4770e",
    "index": 1,
    "skip": 0,
    "timestampUtcMs": "2026-03-23T18:55:03.189Z"
  },
  {
    "action": {
      "input": {
        "rfpId": "922c6e79-25b2-414e-a494-25a3513692d9",
        "title": "RFP-Powerhouse Workstream 2024"
      },
      "scope": "global",
      "type": "SET_REQUEST_FOR_PROPOSAL"
    },
    "error": null,
    "hash": "wZHcECNJjBmewU4vclexM6QfvkA=",
    "id": "16997250a9443fa85e0ffd559bd017cd",
    "index": 2,
    "skip": 0,
    "timestampUtcMs": "2026-03-23T18:55:03.189Z"
  },
  {
    "action": {
      "input": {
        "id": "7f6e94e1-7418-453b-92f9-a93b49f07257",
        "paymentTermsId": "59020cb2-681c-4108-8827-e475de073eec",
        "proposalAuthor": {
          "id": "55b914d4-a738-46a5-bd10-e3627e617c0d",
          "name": "BAI"
        },
        "sowId": "9253cbbd-7577-4c3a-bca6-f54c81c74242",
        "status": "ACCEPTED"
      },
      "scope": "global",
      "type": "EDIT_INITIAL_PROPOSAL"
    },
    "error": null,
    "hash": "SXg8/xygMdzW73FxLAjfzSVfcjE=",
    "id": "788e392aa6ffee015e5d3469950a0739",
    "index": 3,
    "skip": 0,
    "timestampUtcMs": "2026-03-23T18:55:03.189Z"
  },
  {
    "action": {
      "input": {
        "clientId": "078401d0-b861-4fba-a385-5e0dec199813",
        "icon": "https://fusion.sky.money/_next/image?url=https%3A%2F%2Fmakerdao-ses.github.io%2Fecosystem-dashboard%2Fecosystem-actors%2FPOWERHOUSE%2FPOWERHOUSE_logo.png&w=3840&q=85",
        "name": "Powerhouse"
      },
      "scope": "global",
      "type": "EDIT_CLIENT_INFO"
    },
    "error": null,
    "hash": "SqgrWEDcsVyyHH2FZnvPJpRbw2c=",
    "id": "574f3373f1326f38f198eb5b3af58d3b",
    "index": 4,
    "skip": 0,
    "timestampUtcMs": "2026-03-24T14:37:54.277Z"
  },
  {
    "action": {
      "input": {
        "code": "PW2"
      },
      "scope": "global",
      "type": "EDIT_WORKSTREAM"
    },
    "error": null,
    "hash": "/sBwPMjFCk/WdXU09E6sKrMI1Q8=",
    "id": "816a00a659202dab2c26449b7b63536b",
    "index": 5,
    "skip": 0,
    "timestampUtcMs": "2026-03-26T14:03:22.562Z"
  },
  {
    "action": {
      "input": {
        "code": "PW25"
      },
      "scope": "global",
      "type": "EDIT_WORKSTREAM"
    },
    "error": null,
    "hash": "SqgrWEDcsVyyHH2FZnvPJpRbw2c=",
    "id": "018fda245f43aab112321b20ec23596a",
    "index": 6,
    "skip": 0,
    "timestampUtcMs": "2026-03-26T14:03:25.189Z"
  }
]